Metadata-Version: 1.1
Name: wsnotifier
Version: 1.0.4
Summary: Gevent based Asynchronous WebSocket Server with HTTP APIs.
Home-page: UNKNOWN
Author: Sreejith Kesavan
Author-email: sreejithemk@gmail.com
License: UNKNOWN
Keywords: websocket http ws server
Platform: any
Classifier: Development Status :: 5 - Production/Stable
Classifier: Environment :: Web Environment
Classifier: Framework :: Flask
Classifier: Intended Audience :: Developers
Classifier: License :: OSI Approved :: MIT License
Classifier: Operating System :: POSIX
Classifier: Programming Language :: Python
Classifier: Topic :: Internet
Classifier: Topic :: Internet :: WWW/HTTP
Classifier: Topic :: Utilities
